blockxai_chat/__init__.py
blockxai_chat/chatbot.py
blockxai_chat/enhancer.py
blockxai_chat/interface.py
blockxai_chat-0.1.2.dist-info/METADATA
blockxai_chat-0.1.2.dist-info/WHEEL
blockxai_chat-0.1.2.dist-info/entry_points.txt
blockxai_chat-0.1.2.dist-info/top_level.txt
blockxai_chat-0.1.2.dist-info/RECORD
