Metadata-Version: 2.4
Name: blockxai-chat
Version: 0.1.2
Summary: Create AI chatbots with a single prompt
Author-email: BlockXAI <ask@blockxint.com>
License: MIT
Project-URL: Homepage, https://github.com/BlockXAI/blockxai-chat
Project-URL: Bug Tracker, https://github.com/BlockXAI/blockxai-chat/issues
Project-URL: Documentation, https://github.com/BlockXAI/blockxai-chat#readme
Project-URL: Source Code, https://github.com/BlockXAI/blockxai-chat
Classifier: Programming Language :: Python :: 3
Classifier: License :: OSI Approved :: MIT License
Classifier: Operating System :: OS Independent
Requires-Python: >=3.8
Requires-Dist: openai
Requires-Dist: google-generativeai>=0.3.0
Requires-Dist: gradio
Requires-Dist: python-dotenv
